unittest_asserts-0.1.0.dist-info/WHEEL
unittest_asserts-0.1.0.dist-info/top_level.txt
unittest_asserts-0.1.0.dist-info/METADATA
unittest_asserts-0.1.0.dist-info/DESCRIPTION.rst
unittest_asserts-0.1.0.dist-info/metadata.json
unittest_asserts-0.1.0.dist-info/RECORD
asserts/__init__.py
